buf/validate/validate_pb2.py
buf/validate/validate_pb2.pyi
meshtrade/__init__.py
meshtrade/common/__init__.py
meshtrade/common/config.py
meshtrade/common/grpc_client.py
meshtrade/common/service_options.py
meshtrade/compliance/__init__.py
meshtrade/compliance/client/__init__.py
meshtrade/compliance/client/v1/__init__.py
meshtrade/compliance/client/v1/client_pb2.py
meshtrade/compliance/client/v1/client_pb2.pyi
meshtrade/compliance/client/v1/client_pb2_grpc.py
meshtrade/compliance/client/v1/company_pb2.py
meshtrade/compliance/client/v1/company_pb2.pyi
meshtrade/compliance/client/v1/company_pb2_grpc.py
meshtrade/compliance/client/v1/company_representative_pb2.py
meshtrade/compliance/client/v1/company_representative_pb2.pyi
meshtrade/compliance/client/v1/company_representative_pb2_grpc.py
meshtrade/compliance/client/v1/company_representative_role_pb2.py
meshtrade/compliance/client/v1/company_representative_role_pb2.pyi
meshtrade/compliance/client/v1/company_representative_role_pb2_grpc.py
meshtrade/compliance/client/v1/fund_pb2.py
meshtrade/compliance/client/v1/fund_pb2.pyi
meshtrade/compliance/client/v1/fund_pb2_grpc.py
meshtrade/compliance/client/v1/identification_document_type_pb2.py
meshtrade/compliance/client/v1/identification_document_type_pb2.pyi
meshtrade/compliance/client/v1/identification_document_type_pb2_grpc.py
meshtrade/compliance/client/v1/industry_classification_pb2.py
meshtrade/compliance/client/v1/industry_classification_pb2.pyi
meshtrade/compliance/client/v1/industry_classification_pb2_grpc.py
meshtrade/compliance/client/v1/natural_person_connection_type_pb2.py
meshtrade/compliance/client/v1/natural_person_connection_type_pb2.pyi
meshtrade/compliance/client/v1/natural_person_connection_type_pb2_grpc.py
meshtrade/compliance/client/v1/natural_person_pb2.py
meshtrade/compliance/client/v1/natural_person_pb2.pyi
meshtrade/compliance/client/v1/natural_person_pb2_grpc.py
meshtrade/compliance/client/v1/pep_status_pb2.py
meshtrade-1.38.0.dist-info/METADATA
meshtrade-1.38.0.dist-info/WHEEL
meshtrade-1.38.0.dist-info/top_level.txt
meshtrade-1.38.0.dist-info/RECORD
