Metadata-Version: 2.4
Name: meshtrade
Version: 1.38.0
Summary: Integration SDK for Mesh API Services
Author-email: Bernard Bussy <bernard@meshtrade.co>
License: LicenseRef-My-Custom-License
Project-URL: Repository, https://github.com/meshtrade/api
Keywords: meshtrade,mesh,mesh-sdk,grpc,protobuf
Classifier: Development Status :: 1 - Planning
Classifier: Intended Audience :: Developers
Classifier: Topic :: Software Development :: Libraries :: Python Modules
Classifier: Programming Language :: Python :: 3
Classifier: Programming Language :: Python :: 3.12
Classifier: License :: Other/Proprietary License
Requires-Python: >=3.12
Requires-Dist: grpcio<2.0,>=1.74.0
Requires-Dist: protobuf<7.0,>=6.31.1
Requires-Dist: googleapis-common-protos<2.0.0,>=1.70.0
Requires-Dist: protovalidate>=0.13.0
Requires-Dist: platformdirs<5.0,>=4.3.8
Requires-Dist: grpcio-tools>=1.76.0
Requires-Dist: ruff>=0.11.13
Provides-Extra: dev
Requires-Dist: ruff~=0.11.13; extra == "dev"
Requires-Dist: pytest~=8.4.0; extra == "dev"
Requires-Dist: build~=1.2.2; extra == "dev"
Requires-Dist: twine~=6.1.0; extra == "dev"
Requires-Dist: tox~=4.26.0; extra == "dev"
Requires-Dist: types-protobuf~=6.30.2.20250516; extra == "dev"
Requires-Dist: grpcio-tools>=1.74.0; extra == "dev"
Requires-Dist: jinja2>=3.0.0; extra == "dev"
